renga_sphinx_theme/__init__.py
renga_sphinx_theme/about.html
renga_sphinx_theme/layout.html
renga_sphinx_theme/theme.conf
renga_sphinx_theme/version.py
renga_sphinx_theme/static/custom.css
renga_sphinx_theme/static/favicon.png
renga_sphinx_theme-0.1.0.dist-info/DESCRIPTION.rst
renga_sphinx_theme-0.1.0.dist-info/METADATA
renga_sphinx_theme-0.1.0.dist-info/RECORD
renga_sphinx_theme-0.1.0.dist-info/WHEEL
renga_sphinx_theme-0.1.0.dist-info/entry_points.txt
renga_sphinx_theme-0.1.0.dist-info/metadata.json
renga_sphinx_theme-0.1.0.dist-info/top_level.txt
