Metadata-Version: 2.0
Name: renga-sphinx-theme
Version: 0.1.0
Summary: A Sphinx theme for Renga documentation.
Home-page: https://github.com/SwissDataScienceCenter/renga-sphinx-theme
Author: Swiss Data Science Center (SDSC)
Author-email: contact@datascience.ch
License: Apache License 2.0
Keywords: Renga Sphinx theme
Platform: any
Classifier: Intended Audience :: Developers
Classifier: License :: OSI Approved :: Apache Software License
Classifier: Operating System :: OS Independent
Classifier: Topic :: Documentation
Classifier: Topic :: Software Development :: Documentation
Classifier: Programming Language :: Python
Classifier: Programming Language :: Python :: 2.7
Classifier: Programming Language :: Python :: 3.5
Classifier: Programming Language :: Python :: 3.6
Provides-Extra: all
Requires-Dist: Sphinx (>=1.6.3); extra == 'all'
Requires-Dist: check-manifest (>=0.25); extra == 'all'
Requires-Dist: isort (>=4.2.2); extra == 'all'
Requires-Dist: pydocstyle (>=1.0.0); extra == 'all'
Provides-Extra: docs
Requires-Dist: Sphinx (>=1.6.3); extra == 'docs'
Provides-Extra: tests
Requires-Dist: check-manifest (>=0.25); extra == 'tests'
Requires-Dist: isort (>=4.2.2); extra == 'tests'
Requires-Dist: pydocstyle (>=1.0.0); extra == 'tests'
